ezpg/.ezpg.py.swp
ezpg/__init__.py
ezpg/ezpg.py
ezpg-0.1.1b2.dist-info/WHEEL
ezpg-0.1.1b2.dist-info/METADATA
ezpg-0.1.1b2.dist-info/RECORD
